{
  "initial_structure": {
    "@module": "pymatgen.core.structure",
    "@class": "Structure",
    "charge": null,
    "lattice": {
      "matrix": [
        [
          0.0,
          4.2468930196252,
          4.2468930196252
        ],
        [
          4.2468930196252,
          0.0,
          4.2468930196252
        ],
        [
          4.2468930196252,
          4.2468930196252,
          0.0
        ]
      ],
      "a": 6.0060137063015855,
      "b": 6.0060137063015855,
      "c": 6.0060137063015855,
      "alpha": 60.00000000000001,
      "beta": 60.00000000000001,
      "gamma": 60.00000000000001,
      "volume": 153.19477710173544
    },
    "sites": [
      {
        "species": [
          {
            "element": "Mg",
            "occu": 1
          }
        ],
        "abc": [
          0.0,
          0.0,
          0.0
        ],
        "xyz": [
          0.0,
          0.0,
          0.0
        ],
        "label": "Mg"
      },
      {
        "species": [
          {
            "element": "Mg",
            "occu": 1
          }
        ],
        "abc": [
          0.0,
          0.0,
          0.5
        ],
        "xyz": [
          2.1234465098126,
          2.1234465098126,
          0.0
        ],
        "label": "Mg"
      },
      {
        "species": [
          {
            "element": "Mg",
            "occu": 1
          }
        ],
        "abc": [
          0.0,
          0.5,
          0.0
        ],
        "xyz": [
          2.1234465098126,
          0.0,
          2.1234465098126
        ],
        "label": "Mg"
      },
      {
        "species": [
          {
            "element": "Mg",
            "occu": 1
          }
        ],
        "abc": [
          0.0,
          0.5,
          0.5
        ],
        "xyz": [
          4.2468930196252,
          2.1234465098126,
          2.1234465098126
        ],
        "label": "Mg"
      },
      {
        "species": [
          {
            "element": "Mg",
            "occu": 1
          }
        ],
        "abc": [
          0.5,
          0.0,
          0.0
        ],
        "xyz": [
          0.0,
          2.1234465098126,
          2.1234465098126
        ],
        "label": "Mg"
      },
      {
        "species": [
          {
            "element": "Mg",
            "occu": 1
          }
        ],
        "abc": [
          0.5,
          0.0,
          0.5
        ],
        "xyz": [
          2.1234465098126,
          4.2468930196252,
          2.1234465098126
        ],
        "label": "Mg"
      },
      {
        "species": [
          {
            "element": "Mg",
            "occu": 1
          }
        ],
        "abc": [
          0.5,
          0.5,
          0.0
        ],
        "xyz": [
          2.1234465098126,
          2.1234465098126,
          4.2468930196252
        ],
        "label": "Mg"
      },
      {
        "species": [
          {
            "element": "Mg",
            "occu": 1
          }
        ],
        "abc": [
          0.5,
          0.5,
          0.5
        ],
        "xyz": [
          4.2468930196252,
          4.2468930196252,
          4.2468930196252
        ],
        "label": "Mg"
      },
      {
        "species": [
          {
            "element": "O",
            "occu": 1
          }
        ],
        "abc": [
          0.25,
          0.25,
          0.75
        ],
        "xyz": [
          4.2468930196252,
          4.2468930196252,
          2.1234465098126
        ],
        "label": "O"
      },
      {
        "species": [
          {
            "element": "O",
            "occu": 1
          }
        ],
        "abc": [
          0.25,
          0.75,
          0.25
        ],
        "xyz": [
          4.2468930196252,
          2.1234465098126,
          4.2468930196252
        ],
        "label": "O"
      },
      {
        "species": [
          {
            "element": "O",
            "occu": 1
          }
        ],
        "abc": [
          0.25,
          0.74999999999999,
          0.75
        ],
        "xyz": [
          6.370339529437758,
          4.2468930196252,
          4.2468930196251575
        ],
        "label": "O"
      },
      {
        "species": [
          {
            "element": "O",
            "occu": 1
          }
        ],
        "abc": [
          0.75,
          0.25,
          0.25
        ],
        "xyz": [
          2.1234465098126,
          4.2468930196252,
          4.2468930196252
        ],
        "label": "O"
      },
      {
        "species": [
          {
            "element": "O",
            "occu": 1
          }
        ],
        "abc": [
          0.74999999999999,
          0.25,
          0.75
        ],
        "xyz": [
          4.2468930196252,
          6.370339529437758,
          4.2468930196251575
        ],
        "label": "O"
      },
      {
        "species": [
          {
            "element": "O",
            "occu": 1
          }
        ],
        "abc": [
          0.74999999999999,
          0.74999999999999,
          0.25
        ],
        "xyz": [
          4.2468930196251575,
          4.2468930196251575,
          6.370339529437715
        ],
        "label": "O"
      },
      {
        "species": [
          {
            "element": "O",
            "occu": 1
          }
        ],
        "abc": [
          0.74999999999999,
          0.74999999999999,
          0.74999999999999
        ],
        "xyz": [
          6.370339529437715,
          6.370339529437715,
          6.370339529437715
        ],
        "label": "O"
      }
    ]
  },
  "removed_atoms": {
    "8": [
      0.25,
      0.25,
      0.25
    ]
  },
  "inserted_atoms": {},
  "changes_of_num_elements": {
    "O": -1
  },
  "charge": 2,
  "in_name": null,
  "out_name": "O1"
}